esopt
