Metadata-Version: 2.1
Name: essearch
Version: 0.5
Summary: an expand search function of elasticsearch
Author: SayaGugu
Author-email: 2708475759@qq.com
License: apache 3.0
Requires: elasticsearch
Requires: ijson
Requires: pprint
Requires: tqdm
